texmark/__init__.py
texmark/_version.py
texmark/build.py
texmark/logs.py
texmark/sectiontracker.py
texmark/shared.py
texmark/filters/__init__.py
texmark/filters/__main__.py
texmark/filters/download_images.py
texmark/filters/tabular.py
texmark/templates/body.tex
texmark/templates/copernicus/README_copernicus_package_7_11.txt
texmark/templates/copernicus/copernicus.bst
texmark/templates/copernicus/copernicus.cfg
texmark/templates/copernicus/copernicus.cls
texmark/templates/copernicus/pdfscreen.sty
texmark/templates/copernicus/pdfscreencop.sty
texmark/templates/copernicus/template.tex
texmark/templates/default/template.tex
texmark/templates/science/.gitignore
texmark/templates/science/example_figure.eps
texmark/templates/science/example_figure.png
texmark/templates/science/example_figure.ps
texmark/templates/science/readme.txt
texmark/templates/science/scicite.sty
texmark/templates/science/science_template.bib
texmark/templates/science/science_template.tex
texmark/templates/science/sciencemag.bst
texmark/templates/science/template.tex
texmark-0.5.5.dist-info/licenses/LICENSE
texmark-0.5.5.dist-info/METADATA
texmark-0.5.5.dist-info/WHEEL
texmark-0.5.5.dist-info/entry_points.txt
texmark-0.5.5.dist-info/top_level.txt
texmark-0.5.5.dist-info/RECORD
