Metadata-Version: 2.4
Name: texmark
Version: 0.5.5
Summary: Write scientific articles in markdown
Author-email: Mahé Perrette <mahe.perrette@gmail.com>
Project-URL: homepage, https://github.com/perrette/texmark
Requires-Python: >=3.9
License-File: LICENSE
Requires-Dist: pypandoc
Requires-Dist: jinja2
Requires-Dist: pyyaml
Requires-Dist: panflute
Requires-Dist: python-frontmatter
Requires-Dist: requests
Dynamic: license-file
